LICENSE
README.md
pyproject.toml
setup.py
keycloak_scanner/__init__.py
keycloak_scanner/__main__.py
keycloak_scanner/_version.py
keycloak_scanner/constants.py
keycloak_scanner/jwt_attack.py
keycloak_scanner/keycloak_api.py
keycloak_scanner/main.py
keycloak_scanner/masterscanner.py
keycloak_scanner/utils.py
keycloak_scanner.egg-info/PKG-INFO
keycloak_scanner.egg-info/SOURCES.txt
keycloak_scanner.egg-info/dependency_links.txt
keycloak_scanner.egg-info/entry_points.txt
keycloak_scanner.egg-info/not-zip-safe
keycloak_scanner.egg-info/requires.txt
keycloak_scanner.egg-info/top_level.txt
keycloak_scanner/logging/__init__.py
keycloak_scanner/logging/http_logging.py
keycloak_scanner/logging/printlogger.py
keycloak_scanner/logging/root_logger.py
keycloak_scanner/logging/vuln_flag.py
keycloak_scanner/scan_base/__init__.py
keycloak_scanner/scan_base/json_result.py
keycloak_scanner/scan_base/mediator.py
keycloak_scanner/scan_base/scan_results.py
keycloak_scanner/scan_base/scanner.py
keycloak_scanner/scan_base/scanner_exceptions.py
keycloak_scanner/scan_base/session_holder.py
keycloak_scanner/scan_base/types.py
keycloak_scanner/scan_base/wrap.py
keycloak_scanner/scanners/__init__.py
keycloak_scanner/scanners/clientregistration_scanner.py
keycloak_scanner/scanners/clients_scanner.py
keycloak_scanner/scanners/form_post_xss_scanner.py
keycloak_scanner/scanners/login_scanner.py
keycloak_scanner/scanners/none_sign_scanner.py
keycloak_scanner/scanners/open_redirect_scanner.py
keycloak_scanner/scanners/realm_scanner.py
keycloak_scanner/scanners/security_console_scanner.py
keycloak_scanner/scanners/well_known_scanner.py
tests/__init__.py
tests/conftest.py
tests/mock_response.py
tests/test_clientregistration_scanner.py
tests/test_clients_scanner.py
tests/test_form_post_xss_scanner.py
tests/test_keycloak_api.py
tests/test_login_scanner.py
tests/test_masterscanner.py
tests/test_none_sign_scanner.py
tests/test_open_redirect_scanner.py
tests/test_realm_scanner.py
tests/test_scan.py
tests/test_scan_event.py
tests/test_scanner.py
tests/test_security_console_scanner.py
tests/test_start.py
tests/test_types.py
tests/test_well_known_scanner.py