Metadata-Version: 2.1
Name: keycloak-scanner
Version: 1.1.0
Summary: Keycloak vulnerabilities scanner
Home-page: http://github.com/neuronaddict/keycloak-scanner
Author: neuronaddict
Author-email: 
License: Apache 2.0
Platform: UNKNOWN
Classifier: Programming Language :: Python :: 3
Classifier: License :: OSI Approved :: Apache Software License
Classifier: Operating System :: OS Independent
Requires-Python: >=3.6
License-File: LICENSE
